<?xml version="1.0"?>
<config version="11.0.0" urldb="paloaltonetworks" detail-version="11.0.4">
  <devices>
    <entry name="localhost.localdomain">
      <network>
        <logical-router>
          <entry name="vmseries-default-router">
            <vrf>
              <entry name="default">
                <ecmp>
                  <symmetric-return>no</symmetric-return>
                  <strict-source-path>no</strict-source-path>
                  <enable>no</enable>
                  <max-path>2</max-path>
                </ecmp>
                <bgp>
                  <med>
                    <always-compare-med>no</always-compare-med>
                    <deterministic-med-comparison>yes</deterministic-med-comparison>
                  </med>
                  <graceful-restart>
                    <stale-route-time>120</stale-route-time>
                    <max-peer-restart-time>120</max-peer-restart-time>
                    <enable>yes</enable>
                    <local-restart-time>120</local-restart-time>
                  </graceful-restart>
                  <global-bfd>
                    <profile>None</profile>
                  </global-bfd>
                  <install-route>no</install-route>
                  <ecmp-multi-as>no</ecmp-multi-as>
                  <enforce-first-as>yes</enforce-first-as>
                  <fast-external-failover>yes</fast-external-failover>
                  <enable>no</enable>
                  <default-local-preference>100</default-local-preference>
                  <graceful-shutdown>no</graceful-shutdown>
                  <always-advertise-network-route>yes</always-advertise-network-route>
                </bgp>
                <ospfv3>
                  <global-bfd>
                    <profile>None</profile>
                  </global-bfd>
                  <graceful-restart>
                    <enable>yes</enable>
                    <grace-period>120</grace-period>
                    <helper-enable>yes</helper-enable>
                    <strict-LSA-checking>yes</strict-LSA-checking>
                    <max-neighbor-restart-time>140</max-neighbor-restart-time>
                  </graceful-restart>
                  <enable>no</enable>
                  <disable-transit-traffic>no</disable-transit-traffic>
                </ospfv3>
                <rip>
                  <global-bfd>
                    <profile>None</profile>
                  </global-bfd>
                  <enable>no</enable>
                  <default-information-originate>no</default-information-originate>
                </rip>
                <ospf>
                  <global-bfd>
                    <profile>None</profile>
                  </global-bfd>
                  <graceful-restart>
                    <enable>yes</enable>
                    <grace-period>120</grace-period>
                    <helper-enable>yes</helper-enable>
                    <strict-LSA-checking>yes</strict-LSA-checking>
                    <max-neighbor-restart-time>140</max-neighbor-restart-time>
                  </graceful-restart>
                  <enable>no</enable>
                  <rfc1583>no</rfc1583>
                </ospf>
                <admin-dists>
                  <ospf-intra>110</ospf-intra>
                  <ospf-inter>110</ospf-inter>
                  <ospf-ext>110</ospf-ext>
                  <ospfv3-intra>110</ospfv3-intra>
                  <ospfv3-inter>110</ospfv3-inter>
                  <ospfv3-ext>110</ospfv3-ext>
                  <bgp-internal>200</bgp-internal>
                  <bgp-external>20</bgp-external>
                  <bgp-local>20</bgp-local>
                  <rip>120</rip>
                  <static>10</static>
                  <static-ipv6>10</static-ipv6>
                </admin-dists>
              </entry>
            </vrf>
          </entry>
          <entry name="vr1">
            <vrf>
              <entry name="default">
                <ecmp>
                  <symmetric-return>no</symmetric-return>
                  <strict-source-path>no</strict-source-path>
                  <enable>no</enable>
                  <max-path>2</max-path>
                </ecmp>
                <bgp>
                  <med>
                    <always-compare-med>no</always-compare-med>
                    <deterministic-med-comparison>yes</deterministic-med-comparison>
                  </med>
                  <graceful-restart>
                    <stale-route-time>120</stale-route-time>
                    <max-peer-restart-time>120</max-peer-restart-time>
                    <enable>yes</enable>
                    <local-restart-time>120</local-restart-time>
                  </graceful-restart>
                  <global-bfd>
                    <profile>None</profile>
                  </global-bfd>
                  <install-route>no</install-route>
                  <ecmp-multi-as>no</ecmp-multi-as>
                  <enforce-first-as>yes</enforce-first-as>
                  <fast-external-failover>yes</fast-external-failover>
                  <enable>no</enable>
                  <default-local-preference>100</default-local-preference>
                  <graceful-shutdown>no</graceful-shutdown>
                  <always-advertise-network-route>yes</always-advertise-network-route>
                </bgp>
                <ospfv3>
                  <global-bfd>
                    <profile>None</profile>
                  </global-bfd>
                  <graceful-restart>
                    <enable>yes</enable>
                    <grace-period>120</grace-period>
                    <helper-enable>yes</helper-enable>
                    <strict-LSA-checking>yes</strict-LSA-checking>
                    <max-neighbor-restart-time>140</max-neighbor-restart-time>
                  </graceful-restart>
                  <enable>no</enable>
                  <disable-transit-traffic>no</disable-transit-traffic>
                </ospfv3>
                <rip>
                  <global-bfd>
                    <profile>None</profile>
                  </global-bfd>
                  <enable>no</enable>
                  <default-information-originate>no</default-information-originate>
                </rip>
                <ospf>
                  <global-bfd>
                    <profile>None</profile>
                  </global-bfd>
                  <graceful-restart>
                    <enable>yes</enable>
                    <grace-period>120</grace-period>
                    <helper-enable>yes</helper-enable>
                    <strict-LSA-checking>yes</strict-LSA-checking>
                    <max-neighbor-restart-time>140</max-neighbor-restart-time>
                  </graceful-restart>
                  <enable>no</enable>
                  <rfc1583>no</rfc1583>
                </ospf>
                <admin-dists>
                  <ospf-intra>110</ospf-intra>
                  <ospf-inter>110</ospf-inter>
                  <ospf-ext>110</ospf-ext>
                  <ospfv3-intra>110</ospfv3-intra>
                  <ospfv3-inter>110</ospfv3-inter>
                  <ospfv3-ext>110</ospfv3-ext>
                  <bgp-internal>200</bgp-internal>
                  <bgp-external>20</bgp-external>
                  <bgp-local>20</bgp-local>
                  <rip>120</rip>
                  <static>10</static>
                  <static-ipv6>10</static-ipv6>
                </admin-dists>
              </entry>
            </vrf>
          </entry>
        </logical-router>
        <profiles>
          <interface-management-profile>
            <entry name="vmseries-interface-mgmt-profile">
              <http>yes</http>
              <https>yes</https>
            </entry>
            <entry name="BasicProfile">
              <http>yes</http>
              <https>yes</https>
            </entry>
          </interface-management-profile>
          <monitor-profile>
            <entry name="default">
              <interval>3</interval>
              <threshold>5</threshold>
              <action>wait-recover</action>
            </entry>
          </monitor-profile>
        </profiles>
        <interface>
          <ethernet>
            <entry name="ethernet1/1">
              <layer3>
                <ndp-proxy>
                  <enabled>no</enabled>
                </ndp-proxy>
                <sdwan-link-settings>
                  <upstream-nat>
                    <enable>no</enable>
                    <static-ip/>
                  </upstream-nat>
                  <enable>no</enable>
                </sdwan-link-settings>
                <interface-management-profile>vmseries-interface-mgmt-profile</interface-management-profile>
                <lldp>
                  <enable>no</enable>
                </lldp>
                <dhcp-client/>
              </layer3>
            </entry>
          </ethernet>
        </interface>
        <virtual-router>
          <entry name="vmseries-default-router">
            <interface>
              <member>ethernet1/1</member>
            </interface>
          </entry>
          <entry name="default">
            <protocol>
              <bgp>
                <enable>no</enable>
                <dampening-profile>
                  <entry name="default">
                    <cutoff>1.25</cutoff>
                    <reuse>0.5</reuse>
                    <max-hold-time>900</max-hold-time>
                    <decay-half-life-reachable>300</decay-half-life-reachable>
                    <decay-half-life-unreachable>900</decay-half-life-unreachable>
                    <enable>yes</enable>
                  </entry>
                </dampening-profile>
              </bgp>
            </protocol>
          </entry>
        </virtual-router>
        <ike>
          <crypto-profiles>
            <ike-crypto-profiles>
              <entry name="default">
                <encryption>
                  <member>aes-128-cbc</member>
                  <member>3des</member>
                </encryption>
                <hash>
                  <member>sha1</member>
                </hash>
                <dh-group>
                  <member>group2</member>
                </dh-group>
                <lifetime>
                  <hours>8</hours>
                </lifetime>
              </entry>
              <entry name="Suite-B-GCM-128">
                <encryption>
                  <member>aes-128-cbc</member>
                </encryption>
                <hash>
                  <member>sha256</member>
                </hash>
                <dh-group>
                  <member>group19</member>
                </dh-group>
                <lifetime>
                  <hours>8</hours>
                </lifetime>
              </entry>
              <entry name="Suite-B-GCM-256">
                <encryption>
                  <member>aes-256-cbc</member>
                </encryption>
                <hash>
                  <member>sha384</member>
                </hash>
                <dh-group>
                  <member>group20</member>
                </dh-group>
                <lifetime>
                  <hours>8</hours>
                </lifetime>
              </entry>
            </ike-crypto-profiles>
            <ipsec-crypto-profiles>
              <entry name="default">
                <esp>
                  <encryption>
                    <member>aes-128-cbc</member>
                    <member>3des</member>
                  </encryption>
                  <authentication>
                    <member>sha1</member>
                  </authentication>
                </esp>
                <dh-group>group2</dh-group>
                <lifetime>
                  <hours>1</hours>
                </lifetime>
              </entry>
              <entry name="Suite-B-GCM-128">
                <esp>
                  <encryption>
                    <member>aes-128-gcm</member>
                  </encryption>
                  <authentication>
                    <member>none</member>
                  </authentication>
                </esp>
                <dh-group>group19</dh-group>
                <lifetime>
                  <hours>1</hours>
                </lifetime>
              </entry>
              <entry name="Suite-B-GCM-256">
                <esp>
                  <encryption>
                    <member>aes-256-gcm</member>
                  </encryption>
                  <authentication>
                    <member>none</member>
                  </authentication>
                </esp>
                <dh-group>group20</dh-group>
                <lifetime>
                  <hours>1</hours>
                </lifetime>
              </entry>
            </ipsec-crypto-profiles>
            <global-protect-app-crypto-profiles>
              <entry name="default">
                <encryption>
                  <member>aes-128-cbc</member>
                </encryption>
                <authentication>
                  <member>sha1</member>
                </authentication>
              </entry>
            </global-protect-app-crypto-profiles>
          </crypto-profiles>
        </ike>
        <qos>
          <profile>
            <entry name="default">
              <class-bandwidth-type>
                <mbps>
                  <class>
                    <entry name="class1">
                      <priority>real-time</priority>
                    </entry>
                    <entry name="class2">
                      <priority>high</priority>
                    </entry>
                    <entry name="class3">
                      <priority>high</priority>
                    </entry>
                    <entry name="class4">
                      <priority>medium</priority>
                    </entry>
                    <entry name="class5">
                      <priority>medium</priority>
                    </entry>
                    <entry name="class6">
                      <priority>low</priority>
                    </entry>
                    <entry name="class7">
                      <priority>low</priority>
                    </entry>
                    <entry name="class8">
                      <priority>low</priority>
                    </entry>
                  </class>
                </mbps>
              </class-bandwidth-type>
            </entry>
          </profile>
        </qos>
      </network>
      <vsys>
        <entry name="vsys1">
          <zone>
            <entry name="untrust">
              <network>
                <layer3>
                  <member>ethernet1/1</member>
                </layer3>
              </network>
            </entry>
          </zone>
          <import>
            <network>
              <interface>
                <member>ethernet1/1</member>
              </interface>
            </network>
          </import>
          <application/>
          <application-group/>
          <service/>
          <service-group/>
          <schedule/>
          <rulebase>
            <security>
              <rules>
                <entry name="ZT-log4j_BLOCK_INBOUND" uuid="7c264022-613c-4edb-89e7-ce5c61eab5f3">
                  <profile-setting>
                    <profiles>
                      <vulnerability>
                        <member>strict</member>
                      </vulnerability>
                    </profiles>
                  </profile-setting>
                  <to>
                    <member>any</member>
                  </to>
                  <from>
                    <member>any</member>
                  </from>
                  <source>
                    <member>any</member>
                  </source>
                  <destination>
                    <member>VulnerableAPP</member>
                  </destination>
                  <source-user>
                    <member>any</member>
                  </source-user>
                  <category>
                    <member>any</member>
                  </category>
                  <application>
                    <member>any</member>
                  </application>
                  <service>
                    <member>any</member>
                  </service>
                  <source-hip>
                    <member>any</member>
                  </source-hip>
                  <destination-hip>
                    <member>any</member>
                  </destination-hip>
                  <action>allow</action>
                  <log-setting>IoT Security Default Profile</log-setting>
                  <disabled>yes</disabled>
                </entry>
                <entry name="ZT-log4j_BLOCK_OUTBOUND" uuid="03a349dd-4da6-45bb-a2a8-c8a822024ddb">
                  <profile-setting>
                    <profiles>
                      <url-filtering>
                        <member>Outbound-URL</member>
                      </url-filtering>
                      <spyware>
                        <member>Log4j-Outbound-AntiSpyware</member>
                      </spyware>
                    </profiles>
                  </profile-setting>
                  <to>
                    <member>any</member>
                  </to>
                  <from>
                    <member>any</member>
                  </from>
                  <source>
                    <member>VulnerableAPP</member>
                  </source>
                  <destination>
                    <member>any</member>
                  </destination>
                  <source-user>
                    <member>any</member>
                  </source-user>
                  <category>
                    <member>any</member>
                  </category>
                  <application>
                    <member>any</member>
                  </application>
                  <service>
                    <member>any</member>
                  </service>
                  <source-hip>
                    <member>any</member>
                  </source-hip>
                  <destination-hip>
                    <member>any</member>
                  </destination-hip>
                  <action>allow</action>
                  <log-setting>IoT Security Default Profile</log-setting>
                  <disabled>yes</disabled>
                </entry>
                <entry name="ZT-LLDP-RMI_logdj_BLOCK" uuid="b76ddbdc-353c-4e39-bd34-605aef539d42">
                  <to>
                    <member>any</member>
                  </to>
                  <from>
                    <member>any</member>
                  </from>
                  <source>
                    <member>any</member>
                  </source>
                  <destination>
                    <member>any</member>
                  </destination>
                  <source-user>
                    <member>any</member>
                  </source-user>
                  <category>
                    <member>any</member>
                  </category>
                  <application>
                    <member>ldap</member>
                    <member>rmi-iiop</member>
                  </application>
                  <service>
                    <member>any</member>
                  </service>
                  <source-hip>
                    <member>any</member>
                  </source-hip>
                  <destination-hip>
                    <member>any</member>
                  </destination-hip>
                  <action>deny</action>
                  <log-setting>IoT Security Default Profile</log-setting>
                  <disabled>yes</disabled>
                </entry>
                <entry name="ZT-AV-and-URL-Filtering" uuid="ce38de81-5e0b-4502-84fa-d66da323403f">
                  <to>
                    <member>any</member>
                  </to>
                  <from>
                    <member>any</member>
                  </from>
                  <source>
                    <member>any</member>
                  </source>
                  <destination>
                    <member>any</member>
                  </destination>
                  <source-user>
                    <member>any</member>
                  </source-user>
                  <category>
                    <member>any</member>
                  </category>
                  <application>
                    <member>any</member>
                  </application>
                  <service>
                    <member>any</member>
                  </service>
                  <source-hip>
                    <member>any</member>
                  </source-hip>
                  <destination-hip>
                    <member>any</member>
                  </destination-hip>
                  <action>allow</action>
                  <log-setting>IoT Security Default Profile</log-setting>
                  <disabled>yes</disabled>
                </entry>
                <entry name="allow-all" uuid="4b0f7676-be64-4007-a31f-b1d6c1ec3dba">
                  <to>
                    <member>any</member>
                  </to>
                  <from>
                    <member>any</member>
                  </from>
                  <source>
                    <member>any</member>
                  </source>
                  <destination>
                    <member>any</member>
                  </destination>
                  <source-user>
                    <member>any</member>
                  </source-user>
                  <category>
                    <member>any</member>
                  </category>
                  <application>
                    <member>any</member>
                  </application>
                  <service>
                    <member>any</member>
                  </service>
                  <source-hip>
                    <member>any</member>
                  </source-hip>
                  <destination-hip>
                    <member>any</member>
                  </destination-hip>
                  <action>allow</action>
                  <log-setting>IoT Security Default Profile</log-setting>
                </entry>
                <entry name="explicit-deny" uuid="fbb7dcca-418b-4c07-908f-874d38b08f1e">
                  <to>
                    <member>any</member>
                  </to>
                  <from>
                    <member>any</member>
                  </from>
                  <source>
                    <member>any</member>
                  </source>
                  <destination>
                    <member>any</member>
                  </destination>
                  <source-user>
                    <member>any</member>
                  </source-user>
                  <category>
                    <member>any</member>
                  </category>
                  <application>
                    <member>any</member>
                  </application>
                  <service>
                    <member>any</member>
                  </service>
                  <source-hip>
                    <member>any</member>
                  </source-hip>
                  <destination-hip>
                    <member>any</member>
                  </destination-hip>
                  <action>deny</action>
                  <log-setting>IoT Security Default Profile</log-setting>
                </entry>
              </rules>
            </security>
            <default-security-rules>
              <rules/>
            </default-security-rules>
            <application-override>
              <rules/>
            </application-override>
            <decryption>
              <rules/>
            </decryption>
            <tunnel-inspect>
              <rules/>
            </tunnel-inspect>
            <authentication>
              <rules/>
            </authentication>
            <nat>
              <rules/>
            </nat>
            <qos>
              <rules/>
            </qos>
            <pbf>
              <rules/>
            </pbf>
            <sdwan>
              <rules/>
            </sdwan>
            <network-packet-broker>
              <rules/>
            </network-packet-broker>
            <dos>
              <rules/>
            </dos>
          </rulebase>
          <address>
            <entry name="VulnerableAPP">
              <ip-netmask>10.1.1.100</ip-netmask>
            </entry>
          </address>
          <address-group/>
          <external-list/>
          <region/>
          <application-tag/>
          <application-filter/>
          <profile-group/>
          <authentication-object/>
          <device-object/>
          <dynamic-user-group/>
          <tag/>
          <application-status/>
          <threats>
            <vulnerability/>
            <spyware/>
          </threats>
          <profiles>
            <virus>
              <entry name="UTD-AV">
                <decoder>
                  <entry name="ftp">
                    <action>default</action>
                    <wildfire-action>default</wildfire-action>
                    <mlav-action>default</mlav-action>
                  </entry>
                  <entry name="http">
                    <action>default</action>
                    <wildfire-action>default</wildfire-action>
                    <mlav-action>default</mlav-action>
                  </entry>
                  <entry name="http2">
                    <action>default</action>
                    <wildfire-action>default</wildfire-action>
                    <mlav-action>default</mlav-action>
                  </entry>
                  <entry name="imap">
                    <action>default</action>
                    <wildfire-action>default</wildfire-action>
                    <mlav-action>default</mlav-action>
                  </entry>
                  <entry name="pop3">
                    <action>default</action>
                    <wildfire-action>default</wildfire-action>
                    <mlav-action>default</mlav-action>
                  </entry>
                  <entry name="smb">
                    <action>default</action>
                    <wildfire-action>default</wildfire-action>
                    <mlav-action>default</mlav-action>
                  </entry>
                  <entry name="smtp">
                    <action>default</action>
                    <wildfire-action>default</wildfire-action>
                    <mlav-action>default</mlav-action>
                  </entry>
                </decoder>
                <mlav-engine-filebased-enabled>
                  <entry name="Windows Executables">
                    <mlav-policy-action>disable</mlav-policy-action>
                  </entry>
                  <entry name="PowerShell Script 1">
                    <mlav-policy-action>disable</mlav-policy-action>
                  </entry>
                  <entry name="PowerShell Script 2">
                    <mlav-policy-action>disable</mlav-policy-action>
                  </entry>
                  <entry name="Executable Linked Format">
                    <mlav-policy-action>disable</mlav-policy-action>
                  </entry>
                  <entry name="MSOffice">
                    <mlav-policy-action>disable</mlav-policy-action>
                  </entry>
                  <entry name="Shell">
                    <mlav-policy-action>disable</mlav-policy-action>
                  </entry>
                </mlav-engine-filebased-enabled>
              </entry>
            </virus>
            <spyware>
              <entry name="Log4j-Outbound-AntiSpyware">
                <botnet-domains>
                  <lists>
                    <entry name="default-paloalto-dns">
                      <action>
                        <sinkhole/>
                      </action>
                      <packet-capture>disable</packet-capture>
                    </entry>
                  </lists>
                  <dns-security-categories>
                    <entry name="pan-dns-sec-adtracking">
                      <log-level>default</log-level>
                      <action>default</action>
                      <packet-capture>disable</packet-capture>
                    </entry>
                    <entry name="pan-dns-sec-cc">
                      <log-level>default</log-level>
                      <action>default</action>
                      <packet-capture>disable</packet-capture>
                    </entry>
                    <entry name="pan-dns-sec-ddns">
                      <log-level>default</log-level>
                      <action>default</action>
                      <packet-capture>disable</packet-capture>
                    </entry>
                    <entry name="pan-dns-sec-grayware">
                      <log-level>default</log-level>
                      <action>default</action>
                      <packet-capture>disable</packet-capture>
                    </entry>
                    <entry name="pan-dns-sec-malware">
                      <log-level>default</log-level>
                      <action>default</action>
                      <packet-capture>disable</packet-capture>
                    </entry>
                    <entry name="pan-dns-sec-parked">
                      <log-level>default</log-level>
                      <action>default</action>
                      <packet-capture>disable</packet-capture>
                    </entry>
                    <entry name="pan-dns-sec-phishing">
                      <log-level>default</log-level>
                      <action>default</action>
                      <packet-capture>disable</packet-capture>
                    </entry>
                    <entry name="pan-dns-sec-proxy">
                      <log-level>default</log-level>
                      <action>default</action>
                      <packet-capture>disable</packet-capture>
                    </entry>
                    <entry name="pan-dns-sec-recent">
                      <log-level>default</log-level>
                      <action>default</action>
                      <packet-capture>disable</packet-capture>
                    </entry>
                  </dns-security-categories>
                  <sinkhole>
                    <ipv4-address>pan-sinkhole-default-ip</ipv4-address>
                    <ipv6-address>::1</ipv6-address>
                  </sinkhole>
                </botnet-domains>
                <rules>
                  <entry name="critical">
                    <action>
                      <default/>
                    </action>
                    <severity>
                      <member>critical</member>
                      <member>high</member>
                    </severity>
                    <threat-name>any</threat-name>
                    <category>any</category>
                    <packet-capture>disable</packet-capture>
                  </entry>
                </rules>
                <mica-engine-spyware-enabled>
                  <entry name="HTTP Command and Control detector">
                    <inline-policy-action>alert</inline-policy-action>
                  </entry>
                  <entry name="HTTP2 Command and Control detector">
                    <inline-policy-action>alert</inline-policy-action>
                  </entry>
                  <entry name="SSL Command and Control detector">
                    <inline-policy-action>alert</inline-policy-action>
                  </entry>
                  <entry name="Unknown-TCP Command and Control detector">
                    <inline-policy-action>alert</inline-policy-action>
                  </entry>
                  <entry name="Unknown-UDP Command and Control detector">
                    <inline-policy-action>alert</inline-policy-action>
                  </entry>
                </mica-engine-spyware-enabled>
              </entry>
            </spyware>
            <vulnerability/>
            <url-filtering>
              <entry name="Outbound-URL">
                <credential-enforcement>
                  <mode>
                    <disabled/>
                  </mode>
                  <log-severity>medium</log-severity>
                  <block>
                    <member>grayware</member>
                    <member>hacking</member>
                    <member>malware</member>
                    <member>phishing</member>
                    <member>private-ip-addresses</member>
                  </block>
                </credential-enforcement>
                <block>
                  <member>grayware</member>
                  <member>hacking</member>
                  <member>malware</member>
                  <member>phishing</member>
                  <member>private-ip-addresses</member>
                </block>
              </entry>
            </url-filtering>
            <custom-url-category/>
            <file-blocking/>
            <data-filtering/>
            <data-objects/>
            <hip-profiles/>
            <dos-protection/>
            <decryption/>
            <wildfire-analysis/>
            <gtp/>
          </profiles>
        </entry>
      </vsys>
      <deviceconfig>
        <system>
          <type>
            <dhcp-client>
              <send-hostname>yes</send-hostname>
              <send-client-id>yes</send-client-id>
              <accept-dhcp-hostname>no</accept-dhcp-hostname>
              <accept-dhcp-domain>yes</accept-dhcp-domain>
            </dhcp-client>
          </type>
          <update-server>updates.paloaltonetworks.com</update-server>
          <update-schedule>
            <threats>
              <recurring>
                <weekly>
                  <day-of-week>wednesday</day-of-week>
                  <at>01:02</at>
                  <action>download-only</action>
                </weekly>
              </recurring>
            </threats>
          </update-schedule>
          <timezone>US/Pacific</timezone>
          <service>
            <disable-telnet>yes</disable-telnet>
            <disable-http>yes</disable-http>
          </service>
          <hostname>vmseries-ngfw</hostname>
          <panorama>
            <local-panorama/>
          </panorama>
          <dns-setting>
            <servers>
              <primary>169.254.169.254</primary>
              <secondary>4.2.2.2</secondary>
            </servers>
          </dns-setting>
          <login-banner>Welcome to the Palo Alto Networks Ultimate Test Drive workshop</login-banner>
          <device-telemetry>
            <device-health-performance>yes</device-health-performance>
            <product-usage>yes</product-usage>
            <threat-prevention>yes</threat-prevention>
            <region>Americas</region>
          </device-telemetry>
        </system>
        <setting>
          <config>
            <rematch>yes</rematch>
          </config>
          <management>
            <hostname-type-in-syslog>FQDN</hostname-type-in-syslog>
            <initcfg>
              <public-key>c3NoLXJzYSBBQUFBQjNOemFDMXljMkVBQUFBREFRQUJBQUFCQVFEQTBHbjZtSzVYYTFuVU9JemVPalBzM2h5a2dQNWMrWVZBalNOcTFwZEVaRGZ1VDU4cEpGYUxMUmZUejA3b0JlRjFtb2lhVVVScHJUNytEdGkzak52ZTBSTTY4TVB5MTJiVlVKdTlTUW5xVVljSGg2UzFVLzgxellDcmxMaGZ4VHozR3IyTmRyNkR4K3Y5dHdFc0s5Z2FxbkJwQ3NHelZpUW1pa28ycE0vY3l3anhVNHRJWmp2WnBiRHlDTWNnTElubkxVaVpXQjlDTzJlVWE3RDZQTDBhZXNsNFZLQlNvODdZeEg5Y1VCMkZmMmJnYzlhZzVmYThJSFVkU3hQY1FUL0dHcnZqR3ZCZXdJaG8yRWhwRDhtdmJMYURJbDBuRDVUQ1lIOWRXK3NDMlNteHVLSFI3dUhlWW5BMTFTTmNOakVLc0VmYytrcVc2TVQ2dTNGand3N3AgY3Mta2V5Cg==</public-key>
              <type>
                <dhcp-client>
                  <send-hostname>yes</send-hostname>
                  <send-client-id>yes</send-client-id>
                  <accept-dhcp-hostname>no</accept-dhcp-hostname>
                  <accept-dhcp-domain>yes</accept-dhcp-domain>
                </dhcp-client>
              </type>
              <hostname>vmseries-ngfw</hostname>
              <dns-primary>169.254.169.254</dns-primary>
              <dns-secondary>4.2.2.2</dns-secondary>
              <op-command-modes>mgmt-interface-swap</op-command-modes>
            </initcfg>
          </management>
        </setting>
      </deviceconfig>
    </entry>
  </devices>
  <shared>
    <application/>
    <application-group/>
    <service/>
    <service-group/>
    <botnet>
      <configuration>
        <http>
          <dynamic-dns>
            <enabled>yes</enabled>
            <threshold>5</threshold>
          </dynamic-dns>
          <malware-sites>
            <enabled>yes</enabled>
            <threshold>5</threshold>
          </malware-sites>
          <recent-domains>
            <enabled>yes</enabled>
            <threshold>5</threshold>
          </recent-domains>
          <ip-domains>
            <enabled>yes</enabled>
            <threshold>10</threshold>
          </ip-domains>
          <executables-from-unknown-sites>
            <enabled>yes</enabled>
            <threshold>5</threshold>
          </executables-from-unknown-sites>
        </http>
        <other-applications>
          <irc>yes</irc>
        </other-applications>
        <unknown-applications>
          <unknown-tcp>
            <destinations-per-hour>10</destinations-per-hour>
            <sessions-per-hour>10</sessions-per-hour>
            <session-length>
              <maximum-bytes>100</maximum-bytes>
              <minimum-bytes>50</minimum-bytes>
            </session-length>
          </unknown-tcp>
          <unknown-udp>
            <destinations-per-hour>10</destinations-per-hour>
            <sessions-per-hour>10</sessions-per-hour>
            <session-length>
              <maximum-bytes>100</maximum-bytes>
              <minimum-bytes>50</minimum-bytes>
            </session-length>
          </unknown-udp>
        </unknown-applications>
      </configuration>
      <report>
        <topn>100</topn>
        <scheduled>yes</scheduled>
      </report>
    </botnet>
    <log-settings/>
  </shared>
  <mgt-config>
    <users>
      <entry name="admin">
        <phash>$5$abmptklx$UQFWsmo6yjNlKaSXMuHIagNgOpqAqh0zX/uUDceoic1</phash>
        <permissions>
          <role-based>
            <superuser>yes</superuser>
          </role-based>
        </permissions>
        <public-key>c3NoLXJzYSBBQUFBQjNOemFDMXljMkVBQUFBREFRQUJBQUFCQVFEQTBHbjZtSzVYYTFuVU9JemVPalBzM2h5a2dQNWMrWVZBalNOcTFwZEVaRGZ1VDU4cEpGYUxMUmZUejA3b0JlRjFtb2lhVVVScHJUNytEdGkzak52ZTBSTTY4TVB5MTJiVlVKdTlTUW5xVVljSGg2UzFVLzgxellDcmxMaGZ4VHozR3IyTmRyNkR4K3Y5dHdFc0s5Z2FxbkJwQ3NHelZpUW1pa28ycE0vY3l3anhVNHRJWmp2WnBiRHlDTWNnTElubkxVaVpXQjlDTzJlVWE3RDZQTDBhZXNsNFZLQlNvODdZeEg5Y1VCMkZmMmJnYzlhZzVmYThJSFVkU3hQY1FUL0dHcnZqR3ZCZXdJaG8yRWhwRDhtdmJMYURJbDBuRDVUQ1lIOWRXK3NDMlNteHVLSFI3dUhlWW5BMTFTTmNOakVLc0VmYytrcVc2TVQ2dTNGand3N3AgY3Mta2V5Cg==</public-key>
      </entry>
    </users>
    <password-complexity>
      <enabled>yes</enabled>
      <minimum-length>8</minimum-length>
    </password-complexity>
  </mgt-config>
</config>

